setup.py
HadoopCalculator.egg-info/PKG-INFO
HadoopCalculator.egg-info/SOURCES.txt
HadoopCalculator.egg-info/dependency_links.txt
HadoopCalculator.egg-info/top_level.txt
hadoopcalculator/__init__.py
hadoopcalculator/hadoop_calculator.py
scripts/hadoop_calculator