Metadata-Version: 1.0
Name: HadoopCalculator
Version: 1.0
Summary: Hadoop Calculator - Providing an educated guess for performance of your Hadoop cluster
Home-page: http://cloud.github.com/downloads/jonEbird/Hadoop-Utils/hadoop_calculator.py
Author: Jon Miller
Author-email: jonEbird@gmail.com
License: UNKNOWN
Platform: UNKNOWN
Classifier: Development Status :: 4 - Beta
Classifier: Environment :: Console
Classifier: Intended Audience :: Developers
Classifier: Intended Audience :: System Administrators
Classifier: License :: OSI Approved :: Apache Software License
Classifier: Natural Language :: English
Classifier: Topic :: System
Classifier: Topic :: Utilities
